{
"type": "FeatureCollection",
"numberMatched": 5,
"name": "wosis_latest_phetb1",
"features": [
{ "type": "Feature", "properties": { "profile_id": 1084468, "layer_id": 839852, "profile_code": "94P0838", "layer_name": "A", "upper_depth": 0, "lower_depth": 15, "organic_surface": false, "value": "{8.00}", "method_options": "{NULL}", "value_avg": 8.0, "dataset_id": "US-NCSS", "country_name": "Indonesia", "positional_uncertainty": "Circa 100 m", "region": "South-Eastern Asia", "continent": "Asia", "date": "1994-6-28", "licence": "U.S. Public Domain http://www.usa.gov/publicdomain/label/1.0/" }, "geometry": { "type": "Point", "coordinates": [ 119.5031357, -8.5646944 ] } },
{ "type": "Feature", "properties": { "profile_id": 1084467, "layer_id": 839847, "profile_code": "94P0837", "layer_name": "EB", "upper_depth": 0, "lower_depth": 4, "organic_surface": false, "value": "{7.00}", "method_options": "{NULL}", "value_avg": 7.0, "dataset_id": "US-NCSS", "country_name": "Indonesia", "positional_uncertainty": "Circa 100 m", "region": "South-Eastern Asia", "continent": "Asia", "date": "1994-6-27", "licence": "U.S. Public Domain http://www.usa.gov/publicdomain/label/1.0/" }, "geometry": { "type": "Point", "coordinates": [ 119.487831099998999, -8.5419168 ] } },
{ "type": "Feature", "properties": { "profile_id": 1084469, "layer_id": 839860, "profile_code": "94P0839", "layer_name": "", "upper_depth": 0, "lower_depth": 3, "organic_surface": false, "value": "{0.00}", "method_options": "{NULL}", "value_avg": 0.0, "dataset_id": "US-NCSS", "country_name": "Indonesia", "positional_uncertainty": "Circa 100 m", "region": "South-Eastern Asia", "continent": "Asia", "date": "1994-6-29", "licence": "U.S. Public Domain http://www.usa.gov/publicdomain/label/1.0/" }, "geometry": { "type": "Point", "coordinates": [ 119.5001678, -8.5696115 ] } },
{ "type": "Feature", "properties": { "profile_id": 1084470, "layer_id": 839866, "profile_code": "94P0840", "layer_name": "A1", "upper_depth": 0, "lower_depth": 10, "organic_surface": false, "value": "{0.00}", "method_options": "{NULL}", "value_avg": 0.0, "dataset_id": "US-NCSS", "country_name": "Indonesia", "positional_uncertainty": "Circa 100 m", "region": "South-Eastern Asia", "continent": "Asia", "date": "1994-6-30", "licence": "U.S. Public Domain http://www.usa.gov/publicdomain/label/1.0/" }, "geometry": { "type": "Point", "coordinates": [ 119.4660568, -8.5583887 ] } },
{ "type": "Feature", "properties": { "profile_id": 1084466, "layer_id": 839839, "profile_code": "94P0836", "layer_name": "A", "upper_depth": 0, "lower_depth": 12, "organic_surface": false, "value": "{0.00}", "method_options": "{NULL}", "value_avg": 0.0, "dataset_id": "US-NCSS", "country_name": "Indonesia", "positional_uncertainty": "Circa 100 m", "region": "South-Eastern Asia", "continent": "Asia", "date": "1994-6-26", "licence": "U.S. Public Domain http://www.usa.gov/publicdomain/label/1.0/" }, "geometry": { "type": "Point", "coordinates": [ 119.489502, -8.5702496 ] } }
]
}
